_ledcd.pypy37-pp73-i686-linux-gnu.so
ledcd.py
main_LedCD.libs/libglfw-bcf1df30.so.3
main_LedCD-3.0.dist-info/top_level.txt
main_LedCD-3.0.dist-info/RECORD
main_LedCD-3.0.dist-info/WHEEL
main_LedCD-3.0.dist-info/METADATA
