Metadata-Version: 2.1
Name: main-LedCD
Version: 3.0
Summary: Led Cube driver module
Home-page: https://github.com/dk731/3D-Led-Cube
Author: dk731
Author-email: demid.kaidalov@gmail.com
License: UNKNOWN
Platform: UNKNOWN
License-File: LICENSE
